massband/__init__.py
massband/__init__.pyi
massband/abc.py
massband/bond_lifetime.py
massband/cluster_analysis.py
massband/conductivity/__init__.py
massband/conductivity/arrhenius.py
massband/conductivity/einstein_helfand.py
massband/conductivity/ne.py
massband/conftest.py
massband/coordination.py
massband/dataloader.py
massband/diffusion/__init__.py
massband/diffusion/arrhenius.py
massband/diffusion/kinisi_diffusion.py
massband/kinisi.py
massband/nodes.py
massband/pmf.py
massband/radius_of_gyration.py
massband/rdf/__init__.py
massband/rdf/bond_analysis.py
massband/rdf/core.py
massband/rdf/utils.py
massband/rdf_fit.py
massband/rdf_plot.py
massband/rotation/rotational_diffusion.py
massband/rotation/utils.py
massband/utils.py
massband-0.1.3.dist-info/WHEEL
massband-0.1.3.dist-info/entry_points.txt
massband-0.1.3.dist-info/METADATA
massband-0.1.3.dist-info/RECORD
