Metadata-Version: 2.4
Name: massband
Version: 0.1.3
Summary: Molecular dynamics post-processing and analysis package
License-Expression: MIT
Requires-Dist: jax>=0.5.0
Requires-Dist: kinisi>=2.0.0
Requires-Dist: laufband>=0.1.3
Requires-Dist: lazy-loader>=0.4
Requires-Dist: matplotlib>=3.10.3
Requires-Dist: pint>=0.23
Requires-Dist: plotly>=6.2.0
Requires-Dist: rdkit2ase>=0.1.11
Requires-Dist: seaborn>=0.13.2
Requires-Dist: uravu>=1.3.0
Requires-Dist: vesin>=0.3.7
Requires-Dist: znh5md>=0.4.8
Requires-Dist: zntrack>=0.8.8
Requires-Dist: jax[cuda] ; extra == 'cuda'
Requires-Python: >=3.11
Provides-Extra: cuda
